MANIFEST.in
README.rst
setup.py
django_touchnet.egg-info/PKG-INFO
django_touchnet.egg-info/SOURCES.txt
django_touchnet.egg-info/dependency_links.txt
django_touchnet.egg-info/top_level.txt
touchnet/__init__.py
touchnet/admin.py
touchnet/forms.py
touchnet/models.py
touchnet/signals.py
touchnet/tests.py
touchnet/urls.py
touchnet/utils.py
touchnet/views.py
touchnet/templates/touchnet/tags/redirect_tag.html
touchnet/templatetags/__init__.py
touchnet/templatetags/touchnet_extras.py