Metadata-Version: 1.1
Name: django-touchnet
Version: 0.2.2
Summary: A Django app to integrate Touchnet.
Home-page: http://creativemedia.ucdavis.edu/
Author: Creative Media
Author-email: webmaster@creativemedia.ucdavis.edu
License: UNKNOWN
Platform: UNKNOWN
Classifier: Environment :: Web Environment
Classifier: Framework :: Django
Classifier: Intended Audience :: Developers
Classifier: Operating System :: OS Independent
Classifier: Programming Language :: Python
Classifier: Programming Language :: Python :: 2.6
Classifier: Programming Language :: Python :: 2.7
Classifier: Topic :: Internet :: WWW/HTTP
Classifier: Topic :: Internet :: WWW/HTTP :: Dynamic Content
